[{"line":2,"elements":[{"start_timestamp":"2022-12-14T22:49:17.433Z","before":[{"result":{"duration":3912855700,"status":"passed"},"match":{"location":"org.example.Step_Definitions.Hooks.open_browser()"}}],"line":5,"name":"User could register with valid data","description":"","id":"f01-registration-|-user-register-to-e-commerce-website;user-could-register-with-valid-data","after":[{"result":{"duration":3336426100,"status":"passed"},"match":{"location":"org.example.Step_Definitions.Hooks.close_browser()"}}],"type":"scenario","keyword":"Scenario","steps":[{"result":{"duration":627230300,"status":"passed"},"line":6,"name":"user goes to register page","match":{"location":"org.example.Step_Definitions.D01_Registration_StepDefinitions.register_Page()"},"keyword":"Given "},{"result":{"duration":8109349700,"status":"passed"},"line":7,"name":"user enters valid data","match":{"location":"org.example.Step_Definitions.D01_Registration_StepDefinitions.validData()"},"keyword":"When "},{"result":{"duration":3814268400,"status":"passed"},"line":8,"name":"user click on register option","match":{"location":"org.example.Step_Definitions.D01_Registration_StepDefinitions.registerClick()"},"keyword":"And "},{"result":{"duration":35965400,"status":"passed"},"line":9,"name":"user should register successfully","match":{"location":"org.example.Step_Definitions.D01_Registration_StepDefinitions.successful_Registration()"},"keyword":"Then "},{"result":{"duration":56840400,"status":"passed"},"line":10,"name":"registration completion message should appear","match":{"location":"org.example.Step_Definitions.D01_Registration_StepDefinitions.success_message()"},"keyword":"And "}],"tags":[{"name":"@smoke"}]}],"name":"F01_Registration | user register to e-commerce website","description":"","id":"f01-registration-|-user-register-to-e-commerce-website","keyword":"Feature","uri":"file:src/main/resources/Features_Folder/F01_Registration.feature","tags":[{"name":"@smoke","type":"Tag","location":{"line":1,"column":1}}]},{"line":2,"elements":[{"start_timestamp":"2022-12-14T22:49:37.370Z","before":[{"result":{"duration":2749882900,"status":"passed"},"match":{"location":"org.example.Step_Definitions.Hooks.open_browser()"}}],"line":4,"name":"User could log in with valid email and password","description":"","id":"f02-login-|-user-login-to-e-commerce-website;user-could-log-in-with-valid-email-and-password","after":[{"result":{"duration":4051426800,"status":"passed"},"match":{"location":"org.example.Step_Definitions.Hooks.close_browser()"}}],"type":"scenario","keyword":"Scenario","steps":[{"result":{"duration":1078344000,"status":"passed"},"line":5,"name":"user goes to login page","match":{"location":"org.example.Step_Definitions.D02_Login_StepDefinitions.login_Page()"},"keyword":"Given "},{"result":{"duration":610249800,"status":"passed"},"line":6,"name":"user enters \"aessam@gmail.com\" and \"123456\"","match":{"arguments":[{"val":"\"aessam@gmail.com\"","offset":12},{"val":"\"123456\"","offset":35}],"location":"org.example.Step_Definitions.D02_Login_StepDefinitions.loginData(java.lang.String,java.lang.String)"},"keyword":"When "},{"result":{"duration":626754900,"status":"passed"},"line":7,"name":"user click on login button","match":{"location":"org.example.Step_Definitions.D02_Login_StepDefinitions.loginClick()"},"keyword":"And "},{"result":{"duration":8000900,"status":"passed"},"line":8,"name":"user should be login successfully","match":{"location":"org.example.Step_Definitions.D02_Login_StepDefinitions.success_login()"},"keyword":"Then "},{"result":{"duration":49005900,"status":"passed"},"line":9,"name":"user go to the home page","match":{"location":"org.example.Step_Definitions.D02_Login_StepDefinitions.homePage()"},"keyword":"And "}],"tags":[{"name":"@smoke"}]},{"start_timestamp":"2022-12-14T22:49:46.560Z","before":[{"result":{"duration":2415637400,"status":"passed"},"match":{"location":"org.example.Step_Definitions.Hooks.open_browser()"}}],"line":12,"name":"User should not log in with invalid email and password","description":"","id":"f02-login-|-user-login-to-e-commerce-website;user-should-not-log-in-with-invalid-email-and-password","after":[{"result":{"duration":3812164200,"status":"passed"},"match":{"location":"org.example.Step_Definitions.Hooks.close_browser()"}}],"type":"scenario","keyword":"Scenario","steps":[{"result":{"duration":881898800,"status":"passed"},"line":13,"name":"user enters \"ali@gmail.com\" and \"wrongPassword\"","match":{"arguments":[{"val":"\"ali@gmail.com\"","offset":12},{"val":"\"wrongPassword\"","offset":32}],"location":"org.example.Step_Definitions.D02_Login_StepDefinitions.loginData(java.lang.String,java.lang.String)"},"keyword":"When "},{"result":{"duration":351826600,"status":"passed"},"line":14,"name":"user click on login button","match":{"location":"org.example.Step_Definitions.D02_Login_StepDefinitions.loginClick()"},"keyword":"And "},{"result":{"duration":55996900,"status":"passed"},"line":15,"name":"user should not login successfully","match":{"location":"org.example.Step_Definitions.D02_Login_StepDefinitions.failed_login()"},"keyword":"Then "}],"tags":[{"name":"@smoke"}]}],"name":"F02_Login | user login to e-commerce website","description":"","id":"f02-login-|-user-login-to-e-commerce-website","keyword":"Feature","uri":"file:src/main/resources/Features_Folder/F02_Login.feature","tags":[{"name":"@smoke","type":"Tag","location":{"line":1,"column":1}}]},{"line":2,"elements":[{"start_timestamp":"2022-12-14T22:49:54.092Z","before":[{"result":{"duration":2279670800,"status":"passed"},"match":{"location":"org.example.Step_Definitions.Hooks.open_browser()"}}],"line":5,"name":"User could reset his/her password successfully","description":"","id":"f03-password-reset-|-user-reset-password;user-could-reset-his/her-password-successfully","after":[{"result":{"duration":3886554700,"status":"passed"},"match":{"location":"org.example.Step_Definitions.Hooks.close_browser()"}}],"type":"scenario","keyword":"Scenario","steps":[{"result":{"duration":1073071900,"status":"passed"},"line":6,"name":"user goes to login page","match":{"location":"org.example.Step_Definitions.D02_Login_StepDefinitions.login_Page()"},"keyword":"Given "},{"result":{"duration":517673300,"status":"passed"},"line":7,"name":"user click on forgot password","match":{"location":"org.example.Step_Definitions.D03_ResetPassword_StepDefinitions.forgotPassword()"},"keyword":"And "},{"result":{"duration":89095300,"status":"passed"},"line":8,"name":"user enters his registered email","match":{"location":"org.example.Step_Definitions.D03_ResetPassword_StepDefinitions.recoverEmail()"},"keyword":"When "},{"result":{"duration":400013600,"status":"passed"},"line":9,"name":"press on Recover button","match":{"location":"org.example.Step_Definitions.D03_ResetPassword_StepDefinitions.recoverBtn()"},"keyword":"And "},{"result":{"duration":33000800,"status":"passed"},"line":10,"name":"user should reset his password successfully","match":{"location":"org.example.Step_Definitions.D03_ResetPassword_StepDefinitions.successReset()"},"keyword":"Then "}],"tags":[{"name":"@smoke"}]}],"name":"F03_Password Reset | user reset password","description":"","id":"f03-password-reset-|-user-reset-password","keyword":"Feature","uri":"file:src/main/resources/Features_Folder/F03_Reset_Password.feature","tags":[{"name":"@smoke","type":"Tag","location":{"line":1,"column":1}}]},{"line":2,"elements":[{"line":4,"name":"user enters \"aessam@gmail.com\" and \"123456\"","description":"","type":"background","keyword":"Background","steps":[]},{"start_timestamp":"2022-12-14T22:50:02.385Z","before":[{"result":{"duration":1714899500,"status":"passed"},"match":{"location":"org.example.Step_Definitions.Hooks.open_browser()"}}],"line":12,"name":"Logged user could search using product name","description":"","id":"f04-product-search-|-user-search-for-product;logged-user-could-search-using-product-name;;2","after":[{"result":{"duration":3437246500,"status":"passed"},"match":{"location":"org.example.Step_Definitions.Hooks.close_browser()"}}],"type":"scenario","keyword":"Scenario Outline","steps":[{"result":{"duration":114011300,"status":"passed"},"line":7,"name":"user click on search box and write \"book\"","match":{"arguments":[{"val":"\"book\"","offset":35}],"location":"org.example.Step_Definitions.D04_ProductSearch_StepDefinitions.searchBox(java.lang.String)"},"keyword":"When "},{"result":{"duration":702926100,"status":"passed"},"line":8,"name":"user press on the search button","match":{"location":"org.example.Step_Definitions.D04_ProductSearch_StepDefinitions.searchButton()"},"keyword":"And "},{"result":{"duration":175021300,"status":"passed"},"line":9,"name":"\"book\" should appear successfully","match":{"arguments":[{"val":"\"book\"","offset":0}],"location":"org.example.Step_Definitions.D04_ProductSearch_StepDefinitions.productFoundSuccess(java.lang.String)"},"keyword":"Then "}],"tags":[{"name":"@smoke"}]},{"line":4,"name":"user enters \"aessam@gmail.com\" and \"123456\"","description":"","type":"background","keyword":"Background","steps":[]},{"start_timestamp":"2022-12-14T22:50:08.540Z","before":[{"result":{"duration":1728189400,"status":"passed"},"match":{"location":"org.example.Step_Definitions.Hooks.open_browser()"}}],"line":13,"name":"Logged user could search using product name","description":"","id":"f04-product-search-|-user-search-for-product;logged-user-could-search-using-product-name;;3","after":[{"result":{"duration":3821280100,"status":"passed"},"match":{"location":"org.example.Step_Definitions.Hooks.close_browser()"}}],"type":"scenario","keyword":"Scenario Outline","steps":[{"result":{"duration":94006200,"status":"passed"},"line":7,"name":"user click on search box and write \"laptop\"","match":{"arguments":[{"val":"\"laptop\"","offset":35}],"location":"org.example.Step_Definitions.D04_ProductSearch_StepDefinitions.searchBox(java.lang.String)"},"keyword":"When "},{"result":{"duration":645878100,"status":"passed"},"line":8,"name":"user press on the search button","match":{"location":"org.example.Step_Definitions.D04_ProductSearch_StepDefinitions.searchButton()"},"keyword":"And "},{"result":{"duration":100534800,"status":"passed"},"line":9,"name":"\"laptop\" should appear successfully","match":{"arguments":[{"val":"\"laptop\"","offset":0}],"location":"org.example.Step_Definitions.D04_ProductSearch_StepDefinitions.productFoundSuccess(java.lang.String)"},"keyword":"Then "}],"tags":[{"name":"@smoke"}]},{"line":4,"name":"user enters \"aessam@gmail.com\" and \"123456\"","description":"","type":"background","keyword":"Background","steps":[]},{"start_timestamp":"2022-12-14T22:50:14.943Z","before":[{"result":{"duration":1769101100,"status":"passed"},"match":{"location":"org.example.Step_Definitions.Hooks.open_browser()"}}],"line":14,"name":"Logged user could search using product name","description":"","id":"f04-product-search-|-user-search-for-product;logged-user-could-search-using-product-name;;4","after":[{"result":{"duration":3830212500,"status":"passed"},"match":{"location":"org.example.Step_Definitions.Hooks.close_browser()"}}],"type":"scenario","keyword":"Scenario Outline","steps":[{"result":{"duration":103006800,"status":"passed"},"line":7,"name":"user click on search box and write \"nike\"","match":{"arguments":[{"val":"\"nike\"","offset":35}],"location":"org.example.Step_Definitions.D04_ProductSearch_StepDefinitions.searchBox(java.lang.String)"},"keyword":"When "},{"result":{"duration":674204900,"status":"passed"},"line":8,"name":"user press on the search button","match":{"location":"org.example.Step_Definitions.D04_ProductSearch_StepDefinitions.searchButton()"},"keyword":"And "},{"result":{"duration":140009800,"status":"passed"},"line":9,"name":"\"nike\" should appear successfully","match":{"arguments":[{"val":"\"nike\"","offset":0}],"location":"org.example.Step_Definitions.D04_ProductSearch_StepDefinitions.productFoundSuccess(java.lang.String)"},"keyword":"Then "}],"tags":[{"name":"@smoke"}]},{"line":4,"name":"user enters \"aessam@gmail.com\" and \"123456\"","description":"","type":"background","keyword":"Background","steps":[]},{"start_timestamp":"2022-12-14T22:50:21.468Z","before":[{"result":{"duration":1748713800,"status":"passed"},"match":{"location":"org.example.Step_Definitions.Hooks.open_browser()"}}],"line":24,"name":"Logged user could search for product using sku","description":"","id":"f04-product-search-|-user-search-for-product;logged-user-could-search-for-product-using-sku;;2","after":[{"result":{"duration":3672488000,"status":"passed"},"match":{"location":"org.example.Step_Definitions.Hooks.close_browser()"}}],"type":"scenario","keyword":"Scenario Outline","steps":[{"result":{"duration":102003900,"status":"passed"},"line":18,"name":"user click on search box and write \"SCI_FAITH\"","match":{"arguments":[{"val":"\"SCI_FAITH\"","offset":35}],"location":"org.example.Step_Definitions.D04_ProductSearch_StepDefinitions.searchBox(java.lang.String)"},"keyword":"When "},{"result":{"duration":626698000,"status":"passed"},"line":19,"name":"user press on the search button","match":{"location":"org.example.Step_Definitions.D04_ProductSearch_StepDefinitions.searchButton()"},"keyword":"And "},{"result":{"duration":1223886500,"status":"passed"},"line":20,"name":"user click on the product in search result","match":{"location":"org.example.Step_Definitions.D04_ProductSearch_StepDefinitions.clickOnProduct()"},"keyword":"And "},{"result":{"duration":29017300,"status":"passed"},"line":21,"name":"\"SCI_FAITH\" should appear successfully in product page","match":{"arguments":[{"val":"\"SCI_FAITH\"","offset":0}],"location":"org.example.Step_Definitions.D04_ProductSearch_StepDefinitions.serialNFound(java.lang.String)"},"keyword":"Then "}],"tags":[{"name":"@smoke"}]},{"line":4,"name":"user enters \"aessam@gmail.com\" and \"123456\"","description":"","type":"background","keyword":"Background","steps":[]},{"start_timestamp":"2022-12-14T22:50:28.882Z","before":[{"result":{"duration":2146348100,"status":"passed"},"match":{"location":"org.example.Step_Definitions.Hooks.open_browser()"}}],"line":25,"name":"Logged user could search for product using sku","description":"","id":"f04-product-search-|-user-search-for-product;logged-user-could-search-for-product-using-sku;;3","after":[{"result":{"duration":3998914600,"status":"passed"},"match":{"location":"org.example.Step_Definitions.Hooks.close_browser()"}}],"type":"scenario","keyword":"Scenario Outline","steps":[{"result":{"duration":112011700,"status":"passed"},"line":18,"name":"user click on search box and write \"APPLE_CAM\"","match":{"arguments":[{"val":"\"APPLE_CAM\"","offset":35}],"location":"org.example.Step_Definitions.D04_ProductSearch_StepDefinitions.searchBox(java.lang.String)"},"keyword":"When "},{"result":{"duration":672621900,"status":"passed"},"line":19,"name":"user press on the search button","match":{"location":"org.example.Step_Definitions.D04_ProductSearch_StepDefinitions.searchButton()"},"keyword":"And "},{"result":{"duration":1122808200,"status":"passed"},"line":20,"name":"user click on the product in search result","match":{"location":"org.example.Step_Definitions.D04_ProductSearch_StepDefinitions.clickOnProduct()"},"keyword":"And "},{"result":{"duration":28991800,"status":"passed"},"line":21,"name":"\"APPLE_CAM\" should appear successfully in product page","match":{"arguments":[{"val":"\"APPLE_CAM\"","offset":0}],"location":"org.example.Step_Definitions.D04_ProductSearch_StepDefinitions.serialNFound(java.lang.String)"},"keyword":"Then "}],"tags":[{"name":"@smoke"}]},{"line":4,"name":"user enters \"aessam@gmail.com\" and \"123456\"","description":"","type":"background","keyword":"Background","steps":[]},{"start_timestamp":"2022-12-14T22:50:36.976Z","before":[{"result":{"duration":2234305100,"status":"passed"},"match":{"location":"org.example.Step_Definitions.Hooks.open_browser()"}}],"line":26,"name":"Logged user could search for product using sku","description":"","id":"f04-product-search-|-user-search-for-product;logged-user-could-search-for-product-using-sku;;4","after":[{"result":{"duration":4033052600,"status":"passed"},"match":{"location":"org.example.Step_Definitions.Hooks.close_browser()"}}],"type":"scenario","keyword":"Scenario Outline","steps":[{"result":{"duration":102011500,"status":"passed"},"line":18,"name":"user click on search box and write \"SF_PRO_11\"","match":{"arguments":[{"val":"\"SF_PRO_11\"","offset":35}],"location":"org.example.Step_Definitions.D04_ProductSearch_StepDefinitions.searchBox(java.lang.String)"},"keyword":"When "},{"result":{"duration":643980400,"status":"passed"},"line":19,"name":"user press on the search button","match":{"location":"org.example.Step_Definitions.D04_ProductSearch_StepDefinitions.searchButton()"},"keyword":"And "},{"result":{"duration":1162589500,"status":"passed"},"line":20,"name":"user click on the product in search result","match":{"location":"org.example.Step_Definitions.D04_ProductSearch_StepDefinitions.clickOnProduct()"},"keyword":"And "},{"result":{"duration":30009100,"status":"passed"},"line":21,"name":"\"SF_PRO_11\" should appear successfully in product page","match":{"arguments":[{"val":"\"SF_PRO_11\"","offset":0}],"location":"org.example.Step_Definitions.D04_ProductSearch_StepDefinitions.serialNFound(java.lang.String)"},"keyword":"Then "}],"tags":[{"name":"@smoke"}]}],"name":"F04_Product Search | user search for product","description":"","id":"f04-product-search-|-user-search-for-product","keyword":"Feature","uri":"file:src/main/resources/Features_Folder/F04_Product_Search.feature","tags":[{"name":"@smoke","type":"Tag","location":{"line":1,"column":1}}]},{"line":2,"elements":[{"start_timestamp":"2022-12-14T22:50:45.196Z","before":[{"result":{"duration":1717973100,"status":"passed"},"match":{"location":"org.example.Step_Definitions.Hooks.open_browser()"}}],"line":6,"name":"Logged User could choose US currency","description":"","id":"f05-switching-currencies-|-user-switch-between-us-and-euro-currencies;logged-user-could-choose-us-currency","after":[{"result":{"duration":3303291100,"status":"passed"},"match":{"location":"org.example.Step_Definitions.Hooks.close_browser()"}}],"type":"scenario","keyword":"Scenario","steps":[{"result":{"duration":90007800,"status":"passed"},"line":7,"name":"user click on the currency selector and choose the US currency","match":{"location":"org.example.Step_Definitions.D05_SwitchCurrencies_StepDifinitions.usDollar_Selection()"},"keyword":"When "},{"result":{"duration":162982000,"status":"passed"},"line":8,"name":"US dollar symbol is chosen and displayed on all products","match":{"location":"org.example.Step_Definitions.D05_SwitchCurrencies_StepDifinitions.usDollar_Chosen_Successfully()"},"keyword":"Then "}],"tags":[{"name":"@smoke"}]},{"start_timestamp":"2022-12-14T22:50:50.492Z","before":[{"result":{"duration":1722263200,"status":"passed"},"match":{"location":"org.example.Step_Definitions.Hooks.open_browser()"}}],"line":11,"name":"Logged User could choose Euro currency","description":"","id":"f05-switching-currencies-|-user-switch-between-us-and-euro-currencies;logged-user-could-choose-euro-currency","after":[{"result":{"duration":4051905700,"status":"passed"},"match":{"location":"org.example.Step_Definitions.Hooks.close_browser()"}}],"type":"scenario","keyword":"Scenario","steps":[{"result":{"duration":727553000,"status":"passed"},"line":12,"name":"user click on the currency selector and choose the Euro currency","match":{"location":"org.example.Step_Definitions.D05_SwitchCurrencies_StepDifinitions.euro_Selection()"},"keyword":"When "},{"result":{"duration":156906600,"status":"passed"},"line":13,"name":"Euro symbol is chosen and displayed on all products","match":{"location":"org.example.Step_Definitions.D05_SwitchCurrencies_StepDifinitions.Euro_Chosen_Successfully()"},"keyword":"Then "}],"tags":[{"name":"@smoke"}]}],"name":"F05_Switching Currencies | user switch between US and Euro currencies","description":"","id":"f05-switching-currencies-|-user-switch-between-us-and-euro-currencies","keyword":"Feature","uri":"file:src/main/resources/Features_Folder/F05_Switch_Currencies.feature","tags":[{"name":"@smoke","type":"Tag","location":{"line":1,"column":1}}]},{"line":2,"elements":[{"start_timestamp":"2022-12-14T22:50:57.159Z","before":[{"result":{"duration":1754964700,"status":"passed"},"match":{"location":"org.example.Step_Definitions.Hooks.open_browser()"}}],"line":5,"name":"Logged user could hover on different sub categories","description":"","id":"f06-hover-on-categories-|-user-hover-on-categories;logged-user-could-hover-on-different-sub-categories","after":[{"result":{"duration":3914332400,"status":"passed"},"match":{"location":"org.example.Step_Definitions.Hooks.close_browser()"}}],"type":"scenario","keyword":"Scenario","steps":[{"result":{"duration":185659700,"status":"passed"},"line":6,"name":"user select random one of the three main categories","match":{"location":"org.example.Step_Definitions.D06_HoverOnCategories_StepDefinitions.categorySelection()"},"keyword":"When "},{"result":{"duration":920323000,"status":"passed"},"line":7,"name":"user could hover on sub categories of the selected main category","match":{"location":"org.example.Step_Definitions.D06_HoverOnCategories_StepDefinitions.hoverSubCategory()"},"keyword":"Then "}],"tags":[{"name":"@smoke"}]}],"name":"F06_Hover On Categories | user hover on categories","description":"","id":"f06-hover-on-categories-|-user-hover-on-categories","keyword":"Feature","uri":"file:src/main/resources/Features_Folder/F06_HoverOnCategories.feature","tags":[{"name":"@smoke","type":"Tag","location":{"line":1,"column":1}}]},{"line":2,"elements":[{"start_timestamp":"2022-12-14T22:51:03.940Z","before":[{"result":{"duration":1824546200,"status":"passed"},"match":{"location":"org.example.Step_Definitions.Hooks.open_browser()"}}],"line":5,"name":"first slider is clickable on home page","description":"","id":"f07-home-sliders-|-user-clicks-on-home-sliders;first-slider-is-clickable-on-home-page","after":[{"result":{"duration":3777376000,"status":"passed"},"match":{"location":"org.example.Step_Definitions.Hooks.close_browser()"}}],"type":"scenario","keyword":"Scenario","steps":[{"result":{"duration":411557200,"status":"passed"},"line":6,"name":"user clicks on the Nokia Lumia 1020 slider","match":{"location":"org.example.Step_Definitions.D07_HomeSliders_StepDefinitions.click_NokiaSlider()"},"keyword":"When "},{"result":{"error_message":"java.lang.AssertionError: expected [https://demo.nopcommerce.com/iphone-6] but found [https://demo.nopcommerce.com/]\r\n\tat org.testng.Assert.fail(Assert.java:110)\r\n\tat org.testng.Assert.failNotEquals(Assert.java:1413)\r\n\tat org.testng.Assert.assertEqualsImpl(Assert.java:149)\r\n\tat org.testng.Assert.assertEquals(Assert.java:131)\r\n\tat org.testng.Assert.assertEquals(Assert.java:655)\r\n\tat org.testng.Assert.assertEquals(Assert.java:665)\r\n\tat org.example.Step_Definitions.D07_HomeSliders_StepDefinitions.iphone_Page(D07_HomeSliders_StepDefinitions.java:40)\r\n\tat ✽.user should be directed to Nokia Lumia 1020 page(file:///D:/E-Commerce%20Website%20Project/E-Commerce_Website_Testing/src/main/resources/Features_Folder/F07_Home_Sliders.feature:7)\r\n","duration":16073600,"status":"failed"},"line":7,"name":"user should be directed to Nokia Lumia 1020 page","match":{"location":"org.example.Step_Definitions.D07_HomeSliders_StepDefinitions.iphone_Page()"},"keyword":"Then "}],"tags":[{"name":"@smoke"}]},{"start_timestamp":"2022-12-14T22:51:09.987Z","before":[{"result":{"duration":1687127400,"status":"passed"},"match":{"location":"org.example.Step_Definitions.Hooks.open_browser()"}}],"line":11,"name":"second slider is clickable on home page","description":"","id":"f07-home-sliders-|-user-clicks-on-home-sliders;second-slider-is-clickable-on-home-page","after":[{"result":{"duration":3865199500,"status":"passed"},"match":{"location":"org.example.Step_Definitions.Hooks.close_browser()"}}],"type":"scenario","keyword":"Scenario","steps":[{"result":{"duration":421742300,"status":"passed"},"line":12,"name":"user clicks on the iPhone slider","match":{"location":"org.example.Step_Definitions.D07_HomeSliders_StepDefinitions.click_IPhoneSlider()"},"keyword":"When "},{"result":{"error_message":"java.lang.AssertionError: expected [https://demo.nopcommerce.com/nokia-lumia-1020] but found [https://demo.nopcommerce.com/]\r\n\tat org.testng.Assert.fail(Assert.java:110)\r\n\tat org.testng.Assert.failNotEquals(Assert.java:1413)\r\n\tat org.testng.Assert.assertEqualsImpl(Assert.java:149)\r\n\tat org.testng.Assert.assertEquals(Assert.java:131)\r\n\tat org.testng.Assert.assertEquals(Assert.java:655)\r\n\tat org.testng.Assert.assertEquals(Assert.java:665)\r\n\tat org.example.Step_Definitions.D07_HomeSliders_StepDefinitions.nokia_Page(D07_HomeSliders_StepDefinitions.java:25)\r\n\tat ✽.user should be directed to iPhone page(file:///D:/E-Commerce%20Website%20Project/E-Commerce_Website_Testing/src/main/resources/Features_Folder/F07_Home_Sliders.feature:13)\r\n","duration":9992000,"status":"failed"},"line":13,"name":"user should be directed to iPhone page","match":{"location":"org.example.Step_Definitions.D07_HomeSliders_StepDefinitions.nokia_Page()"},"keyword":"Then "}],"tags":[{"name":"@smoke"}]}],"name":"F07_Home Sliders | user clicks on home sliders","description":"","id":"f07-home-sliders-|-user-clicks-on-home-sliders","keyword":"Feature","uri":"file:src/main/resources/Features_Folder/F07_Home_Sliders.feature","tags":[{"name":"@smoke","type":"Tag","location":{"line":1,"column":1}}]},{"line":2,"elements":[{"start_timestamp":"2022-12-14T22:51:15.980Z","before":[{"result":{"duration":1797249500,"status":"passed"},"match":{"location":"org.example.Step_Definitions.Hooks.open_browser()"}}],"line":5,"name":"user opens facebook link","description":"","id":"f08-follow-us--|-user-clicks-on-follow-us-icons;user-opens-facebook-link","after":[{"result":{"duration":3328843900,"status":"passed"},"match":{"location":"org.example.Step_Definitions.Hooks.close_browser()"}}],"type":"scenario","keyword":"Scenario","steps":[{"result":{"duration":93008500,"status":"passed"},"line":6,"name":"user clicks on facebook link","match":{"location":"org.example.Step_Definitions.D08_FollowUs_StepDefinitions.click_facebook()"},"keyword":"When "},{"result":{"duration":3026907100,"status":"passed"},"line":7,"name":"user should be directed to the website facabook page","match":{"location":"org.example.Step_Definitions.D08_FollowUs_StepDefinitions.facebookPage()"},"keyword":"Then "}],"tags":[{"name":"@smoke"}]},{"start_timestamp":"2022-12-14T22:51:24.238Z","before":[{"result":{"duration":1845140000,"status":"passed"},"match":{"location":"org.example.Step_Definitions.Hooks.open_browser()"}}],"line":10,"name":"user opens twitter link","description":"","id":"f08-follow-us--|-user-clicks-on-follow-us-icons;user-opens-twitter-link","after":[{"result":{"duration":3350292100,"status":"passed"},"match":{"location":"org.example.Step_Definitions.Hooks.close_browser()"}}],"type":"scenario","keyword":"Scenario","steps":[{"result":{"duration":97008600,"status":"passed"},"line":11,"name":"user clicks on twitter link","match":{"location":"org.example.Step_Definitions.D08_FollowUs_StepDefinitions.click_twitter()"},"keyword":"When "},{"result":{"duration":3181972100,"status":"passed"},"line":12,"name":"user should be directed to the website twitter page","match":{"location":"org.example.Step_Definitions.D08_FollowUs_StepDefinitions.twitter()"},"keyword":"Then "}],"tags":[{"name":"@smoke"}]},{"start_timestamp":"2022-12-14T22:51:32.724Z","before":[{"result":{"duration":1748716900,"status":"passed"},"match":{"location":"org.example.Step_Definitions.Hooks.open_browser()"}}],"line":15,"name":"user opens rss link","description":"","id":"f08-follow-us--|-user-clicks-on-follow-us-icons;user-opens-rss-link","after":[{"result":{"duration":3269012900,"status":"passed"},"match":{"location":"org.example.Step_Definitions.Hooks.close_browser()"}}],"type":"scenario","keyword":"Scenario","steps":[{"result":{"duration":375032000,"status":"passed"},"line":16,"name":"user clicks on rss link","match":{"location":"org.example.Step_Definitions.D08_FollowUs_StepDefinitions.click_rss()"},"keyword":"When "},{"result":{"error_message":"java.lang.IndexOutOfBoundsException: Index 1 out of bounds for length 1\r\n\tat java.base/jdk.internal.util.Preconditions.outOfBounds(Preconditions.java:100)\r\n\tat java.base/jdk.internal.util.Preconditions.outOfBoundsCheckIndex(Preconditions.java:106)\r\n\tat java.base/jdk.internal.util.Preconditions.checkIndex(Preconditions.java:302)\r\n\tat java.base/java.util.Objects.checkIndex(Objects.java:385)\r\n\tat java.base/java.util.ArrayList.get(ArrayList.java:427)\r\n\tat org.example.Step_Definitions.D08_FollowUs_StepDefinitions.rss(D08_FollowUs_StepDefinitions.java:73)\r\n\tat ✽.user should be directed to the website rss page(file:///D:/E-Commerce%20Website%20Project/E-Commerce_Website_Testing/src/main/resources/Features_Folder/F08_FollowUs.feature:17)\r\n","duration":3013816300,"status":"failed"},"line":17,"name":"user should be directed to the website rss page","match":{"location":"org.example.Step_Definitions.D08_FollowUs_StepDefinitions.rss()"},"keyword":"Then "}],"tags":[{"name":"@smoke"}]},{"start_timestamp":"2022-12-14T22:51:41.140Z","before":[{"result":{"duration":1699482400,"status":"passed"},"match":{"location":"org.example.Step_Definitions.Hooks.open_browser()"}}],"line":20,"name":"user opens youtube link","description":"","id":"f08-follow-us--|-user-clicks-on-follow-us-icons;user-opens-youtube-link","after":[{"result":{"duration":3954074700,"status":"passed"},"match":{"location":"org.example.Step_Definitions.Hooks.close_browser()"}}],"type":"scenario","keyword":"Scenario","steps":[{"result":{"duration":111007300,"status":"passed"},"line":21,"name":"user clicks on youtube link","match":{"location":"org.example.Step_Definitions.D08_FollowUs_StepDefinitions.click_youtube()"},"keyword":"When "},{"result":{"duration":4557916500,"status":"passed"},"line":22,"name":"user should be directed to the website youtube page","match":{"location":"org.example.Step_Definitions.D08_FollowUs_StepDefinitions.youtube()"},"keyword":"Then "}],"tags":[{"name":"@smoke"}]}],"name":"F08_Follow Us  | User clicks on follow us icons","description":"","id":"f08-follow-us--|-user-clicks-on-follow-us-icons","keyword":"Feature","uri":"file:src/main/resources/Features_Folder/F08_FollowUs.feature","tags":[{"name":"@smoke","type":"Tag","location":{"line":1,"column":1}}]},{"line":2,"elements":[{"start_timestamp":"2022-12-14T22:51:51.469Z","before":[{"result":{"duration":2249528600,"status":"passed"},"match":{"location":"org.example.Step_Definitions.Hooks.open_browser()"}}],"line":4,"name":"user could add different products to Wishlist","description":"","id":"f09-wishlist-|-user-add-products-to-wishlist;user-could-add-different-products-to-wishlist","after":[{"result":{"duration":3295949200,"status":"passed"},"match":{"location":"org.example.Step_Definitions.Hooks.close_browser()"}}],"type":"scenario","keyword":"Scenario","steps":[{"result":{"duration":69006300,"status":"passed"},"line":5,"name":"user clicks on the wishlist button","match":{"location":"org.example.Step_Definitions.D09_Wishlist_StepDefinitions.click_wishlist()"},"keyword":"When "},{"result":{"duration":304725100,"status":"passed"},"line":6,"name":"the product is added to wishlist and success message appears","match":{"location":"org.example.Step_Definitions.D09_Wishlist_StepDefinitions.wishlist_success()"},"keyword":"Then "}],"tags":[{"name":"@smoke"}]},{"start_timestamp":"2022-12-14T22:51:57.395Z","before":[{"result":{"duration":1647858100,"status":"passed"},"match":{"location":"org.example.Step_Definitions.Hooks.open_browser()"}}],"line":9,"name":"user could click on \"Wishlist\" Tab","description":"","id":"f09-wishlist-|-user-add-products-to-wishlist;user-could-click-on-\"wishlist\"-tab","after":[{"result":{"duration":3257234400,"status":"passed"},"match":{"location":"org.example.Step_Definitions.Hooks.close_browser()"}}],"type":"scenario","keyword":"Scenario","steps":[{"result":{"duration":64004400,"status":"passed"},"line":10,"name":"user clicks on the wishlist button","match":{"location":"org.example.Step_Definitions.D09_Wishlist_StepDefinitions.click_wishlist()"},"keyword":"When "},{"result":{"duration":15549888700,"status":"passed"},"line":11,"name":"user waits until success message disappears and clicks on wishlist Tab","match":{"location":"org.example.Step_Definitions.D09_Wishlist_StepDefinitions.click_wishlistTab()"},"keyword":"And "},{"result":{"duration":37002700,"status":"passed"},"line":12,"name":"product is existed in the wishlist","match":{"location":"org.example.Step_Definitions.D09_Wishlist_StepDefinitions.product_exists()"},"keyword":"Then "}],"tags":[{"name":"@smoke"}]}],"name":"F09_Wishlist | user add products to wishlist","description":"","id":"f09-wishlist-|-user-add-products-to-wishlist","keyword":"Feature","uri":"file:src/main/resources/Features_Folder/F09_Wishlist.feature","tags":[{"name":"@smoke","type":"Tag","location":{"line":1,"column":1}}]}]