[{"line":2,"elements":[{"start_timestamp":"2022-12-14T22:01:38.304Z","before":[{"result":{"duration":5171292500,"status":"passed"},"match":{"location":"org.example.Step_Definitions.Hooks.open_browser()"}}],"line":5,"name":"User could register with valid data","description":"","id":"f01-registration-|-user-register-to-e-commerce-website;user-could-register-with-valid-data","after":[{"result":{"duration":3314841200,"status":"passed"},"match":{"location":"org.example.Step_Definitions.Hooks.close_browser()"}}],"type":"scenario","keyword":"Scenario","steps":[{"result":{"duration":1201003600,"status":"passed"},"line":6,"name":"user goes to register page","match":{"location":"org.example.Step_Definitions.D01_Registration_StepDefinitions.register_Page()"},"keyword":"Given "},{"result":{"duration":8115271800,"status":"passed"},"line":7,"name":"user enters valid data","match":{"location":"org.example.Step_Definitions.D01_Registration_StepDefinitions.validData()"},"keyword":"When "},{"result":{"duration":3885143700,"status":"passed"},"line":8,"name":"user click on register option","match":{"location":"org.example.Step_Definitions.D01_Registration_StepDefinitions.registerClick()"},"keyword":"And "},{"result":{"error_message":"org.openqa.selenium.NoSuchElementException: no such element: Unable to locate element: {\"method\":\"css selector\",\"selector\":\".ico\\-logout\"}\n  (Session info: chrome=108.0.5359.100)\nFor documentation on this error, please visit: https://selenium.dev/exceptions/#no_such_element\nBuild info: version: '4.7.1', revision: 'c6795baf1a3'\nSystem info: os.name: 'Windows 10', os.arch: 'amd64', os.version: '10.0', java.version: '19.0.1'\nDriver info: org.openqa.selenium.chrome.ChromeDriver\nCommand: [89a6438cff1ebee742759c4d02f168d5, findElement {using=class name, value=ico-logout}]\nCapabilities {acceptInsecureCerts: false, browserName: chrome, browserVersion: 108.0.5359.100, chrome: {chromedriverVersion: 108.0.5359.71 (1e0e3868ee06..., userDataDir: C:\\Users\\745G5~1\\AppData\\Lo...}, goog:chromeOptions: {debuggerAddress: localhost:51503}, networkConnectionEnabled: false, pageLoadStrategy: normal, platformName: WINDOWS, proxy: Proxy(), se:cdp: ws://localhost:51503/devtoo..., se:cdpVersion: 108.0.5359.100, setWindowRect: true, strictFileInteractability: false, timeouts: {implicit: 0, pageLoad: 300000, script: 30000}, unhandledPromptBehavior: dismiss and notify, webauthn:extension:credBlob: true, webauthn:extension:largeBlob: true, webauthn:virtualAuthenticators: true}\nSession ID: 89a6438cff1ebee742759c4d02f168d5\r\n\tat java.base/jdk.internal.reflect.DirectConstructorHandleAccessor.newInstance(DirectConstructorHandleAccessor.java:67)\r\n\tat java.base/java.lang.reflect.Constructor.newInstanceWithCaller(Constructor.java:500)\r\n\tat java.base/java.lang.reflect.Constructor.newInstance(Constructor.java:484)\r\n\tat org.openqa.selenium.remote.codec.w3c.W3CHttpResponseCodec.createException(W3CHttpResponseCodec.java:200)\r\n\tat org.openqa.selenium.remote.codec.w3c.W3CHttpResponseCodec.decode(W3CHttpResponseCodec.java:133)\r\n\tat org.openqa.selenium.remote.codec.w3c.W3CHttpResponseCodec.decode(W3CHttpResponseCodec.java:53)\r\n\tat org.openqa.selenium.remote.HttpCommandExecutor.execute(HttpCommandExecutor.java:184)\r\n\tat org.openqa.selenium.remote.service.DriverCommandExecutor.invokeExecute(DriverCommandExecutor.java:167)\r\n\tat org.openqa.selenium.remote.service.DriverCommandExecutor.execute(DriverCommandExecutor.java:142)\r\n\tat org.openqa.selenium.remote.RemoteWebDriver.execute(RemoteWebDriver.java:551)\r\n\tat org.openqa.selenium.remote.ElementLocation$ElementFinder$2.findElement(ElementLocation.java:162)\r\n\tat org.openqa.selenium.remote.ElementLocation.findElement(ElementLocation.java:60)\r\n\tat org.openqa.selenium.remote.RemoteWebDriver.findElement(RemoteWebDriver.java:367)\r\n\tat org.openqa.selenium.remote.RemoteWebDriver.findElement(RemoteWebDriver.java:359)\r\n\tat org.example.Step_Definitions.D01_Registration_StepDefinitions.successful_Registration(D01_Registration_StepDefinitions.java:78)\r\n\tat ✽.user should register successfully(file:///D:/E-Commerce%20Website%20Project/E-Commerce_Website_Testing/src/main/resources/Features_Folder/F01_Registration.feature:9)\r\n","duration":10045692300,"status":"failed"},"line":9,"name":"user should register successfully","match":{"location":"org.example.Step_Definitions.D01_Registration_StepDefinitions.successful_Registration()"},"keyword":"Then "},{"result":{"status":"skipped"},"line":10,"name":"registration completion message should appear","match":{"location":"org.example.Step_Definitions.D01_Registration_StepDefinitions.success_message()"},"keyword":"And "}],"tags":[{"name":"@smoke"}]}],"name":"F01_Registration | user register to e-commerce website","description":"","id":"f01-registration-|-user-register-to-e-commerce-website","keyword":"Feature","uri":"file:src/main/resources/Features_Folder/F01_Registration.feature","tags":[{"name":"@smoke","type":"Tag","location":{"line":1,"column":1}}]},{"line":2,"elements":[{"start_timestamp":"2022-12-14T22:02:10.083Z","before":[{"result":{"duration":2228336200,"status":"passed"},"match":{"location":"org.example.Step_Definitions.Hooks.open_browser()"}}],"line":4,"name":"User could log in with valid email and password","description":"","id":"f02-login-|-user-login-to-e-commerce-website;user-could-log-in-with-valid-email-and-password","after":[{"result":{"duration":3412253300,"status":"passed"},"match":{"location":"org.example.Step_Definitions.Hooks.close_browser()"}}],"type":"scenario","keyword":"Scenario","steps":[{"result":{"duration":1078298900,"status":"passed"},"line":5,"name":"user goes to login page","match":{"location":"org.example.Step_Definitions.D02_Login_StepDefinitions.login_Page()"},"keyword":"Given "},{"result":{"duration":616007500,"status":"passed"},"line":6,"name":"user enters \"aessam@gmail.com\" and \"123456\"","match":{"arguments":[{"val":"\"aessam@gmail.com\"","offset":12},{"val":"\"123456\"","offset":35}],"location":"org.example.Step_Definitions.D02_Login_StepDefinitions.loginData(java.lang.String,java.lang.String)"},"keyword":"When "},{"result":{"duration":659150000,"status":"passed"},"line":7,"name":"user click on login button","match":{"location":"org.example.Step_Definitions.D02_Login_StepDefinitions.loginClick()"},"keyword":"And "},{"result":{"duration":14996000,"status":"passed"},"line":8,"name":"user should be login successfully","match":{"location":"org.example.Step_Definitions.D02_Login_StepDefinitions.success_login()"},"keyword":"Then "},{"result":{"duration":45004600,"status":"passed"},"line":9,"name":"user go to the home page","match":{"location":"org.example.Step_Definitions.D02_Login_StepDefinitions.homePage()"},"keyword":"And "}],"tags":[{"name":"@smoke"}]},{"start_timestamp":"2022-12-14T22:02:18.151Z","before":[{"result":{"duration":2174582600,"status":"passed"},"match":{"location":"org.example.Step_Definitions.Hooks.open_browser()"}}],"line":12,"name":"User should not log in with invalid email and password","description":"","id":"f02-login-|-user-login-to-e-commerce-website;user-should-not-log-in-with-invalid-email-and-password","after":[{"result":{"duration":4248911500,"status":"passed"},"match":{"location":"org.example.Step_Definitions.Hooks.close_browser()"}}],"type":"scenario","keyword":"Scenario","steps":[{"result":{"duration":1346650900,"status":"passed"},"line":13,"name":"user enters \"ali@gmail.com\" and \"wrongPassword\"","match":{"arguments":[{"val":"\"ali@gmail.com\"","offset":12},{"val":"\"wrongPassword\"","offset":32}],"location":"org.example.Step_Definitions.D02_Login_StepDefinitions.loginData(java.lang.String,java.lang.String)"},"keyword":"When "},{"result":{"duration":840821600,"status":"passed"},"line":14,"name":"user click on login button","match":{"location":"org.example.Step_Definitions.D02_Login_StepDefinitions.loginClick()"},"keyword":"And "},{"result":{"duration":58002800,"status":"passed"},"line":15,"name":"user should not login successfully","match":{"location":"org.example.Step_Definitions.D02_Login_StepDefinitions.failed_login()"},"keyword":"Then "}],"tags":[{"name":"@smoke"}]}],"name":"F02_Login | user login to e-commerce website","description":"","id":"f02-login-|-user-login-to-e-commerce-website","keyword":"Feature","uri":"file:src/main/resources/Features_Folder/F02_Login.feature","tags":[{"name":"@smoke","type":"Tag","location":{"line":1,"column":1}}]},{"line":2,"elements":[{"start_timestamp":"2022-12-14T22:02:26.833Z","before":[{"result":{"duration":1808493200,"status":"passed"},"match":{"location":"org.example.Step_Definitions.Hooks.open_browser()"}}],"line":5,"name":"User could reset his/her password successfully","description":"","id":"f03-password-reset-|-user-reset-password;user-could-reset-his/her-password-successfully","after":[{"result":{"duration":3280552300,"status":"passed"},"match":{"location":"org.example.Step_Definitions.Hooks.close_browser()"}}],"type":"scenario","keyword":"Scenario","steps":[{"result":{"duration":632322300,"status":"passed"},"line":6,"name":"user goes to login page","match":{"location":"org.example.Step_Definitions.D02_Login_StepDefinitions.login_Page()"},"keyword":"Given "},{"result":{"duration":496990300,"status":"passed"},"line":7,"name":"user click on forgot password","match":{"location":"org.example.Step_Definitions.D03_ResetPassword_StepDefinitions.forgotPassword()"},"keyword":"And "},{"result":{"duration":90924900,"status":"passed"},"line":8,"name":"user enters his registered email","match":{"location":"org.example.Step_Definitions.D03_ResetPassword_StepDefinitions.recoverEmail()"},"keyword":"When "},{"result":{"duration":419854200,"status":"passed"},"line":9,"name":"press on Recover button","match":{"location":"org.example.Step_Definitions.D03_ResetPassword_StepDefinitions.recoverBtn()"},"keyword":"And "},{"result":{"duration":31001000,"status":"passed"},"line":10,"name":"user should reset his password successfully","match":{"location":"org.example.Step_Definitions.D03_ResetPassword_StepDefinitions.successReset()"},"keyword":"Then "}],"tags":[{"name":"@smoke"}]}],"name":"F03_Password Reset | user reset password","description":"","id":"f03-password-reset-|-user-reset-password","keyword":"Feature","uri":"file:src/main/resources/Features_Folder/F03_Reset_Password.feature","tags":[{"name":"@smoke","type":"Tag","location":{"line":1,"column":1}}]},{"line":2,"elements":[{"line":4,"name":"user enters \"aessam@gmail.com\" and \"123456\"","description":"","type":"background","keyword":"Background","steps":[]},{"start_timestamp":"2022-12-14T22:02:33.608Z","before":[{"result":{"duration":1693922400,"status":"passed"},"match":{"location":"org.example.Step_Definitions.Hooks.open_browser()"}}],"line":12,"name":"Logged user could search using product name","description":"","id":"f04-product-search-|-user-search-for-product;logged-user-could-search-using-product-name;;2","after":[{"result":{"duration":4181819300,"status":"passed"},"match":{"location":"org.example.Step_Definitions.Hooks.close_browser()"}}],"type":"scenario","keyword":"Scenario Outline","steps":[{"result":{"duration":89008000,"status":"passed"},"line":7,"name":"user click on search box and write \"book\"","match":{"arguments":[{"val":"\"book\"","offset":35}],"location":"org.example.Step_Definitions.D04_ProductSearch_StepDefinitions.searchBox(java.lang.String)"},"keyword":"When "},{"result":{"duration":692121800,"status":"passed"},"line":8,"name":"user press on the search button","match":{"location":"org.example.Step_Definitions.D04_ProductSearch_StepDefinitions.searchButton()"},"keyword":"And "},{"result":{"duration":158391200,"status":"passed"},"line":9,"name":"\"book\" should appear successfully","match":{"arguments":[{"val":"\"book\"","offset":0}],"location":"org.example.Step_Definitions.D04_ProductSearch_StepDefinitions.productFoundSuccess(java.lang.String)"},"keyword":"Then "}],"tags":[{"name":"@smoke"}]},{"line":4,"name":"user enters \"aessam@gmail.com\" and \"123456\"","description":"","type":"background","keyword":"Background","steps":[]},{"start_timestamp":"2022-12-14T22:02:40.436Z","before":[{"result":{"duration":1772446300,"status":"passed"},"match":{"location":"org.example.Step_Definitions.Hooks.open_browser()"}}],"line":13,"name":"Logged user could search using product name","description":"","id":"f04-product-search-|-user-search-for-product;logged-user-could-search-using-product-name;;3","after":[{"result":{"duration":3295335200,"status":"passed"},"match":{"location":"org.example.Step_Definitions.Hooks.close_browser()"}}],"type":"scenario","keyword":"Scenario Outline","steps":[{"result":{"duration":92008300,"status":"passed"},"line":7,"name":"user click on search box and write \"laptop\"","match":{"arguments":[{"val":"\"laptop\"","offset":35}],"location":"org.example.Step_Definitions.D04_ProductSearch_StepDefinitions.searchBox(java.lang.String)"},"keyword":"When "},{"result":{"duration":668921400,"status":"passed"},"line":8,"name":"user press on the search button","match":{"location":"org.example.Step_Definitions.D04_ProductSearch_StepDefinitions.searchButton()"},"keyword":"And "},{"result":{"duration":92797000,"status":"passed"},"line":9,"name":"\"laptop\" should appear successfully","match":{"arguments":[{"val":"\"laptop\"","offset":0}],"location":"org.example.Step_Definitions.D04_ProductSearch_StepDefinitions.productFoundSuccess(java.lang.String)"},"keyword":"Then "}],"tags":[{"name":"@smoke"}]},{"line":4,"name":"user enters \"aessam@gmail.com\" and \"123456\"","description":"","type":"background","keyword":"Background","steps":[]},{"start_timestamp":"2022-12-14T22:02:46.369Z","before":[{"result":{"duration":2143582500,"status":"passed"},"match":{"location":"org.example.Step_Definitions.Hooks.open_browser()"}}],"line":14,"name":"Logged user could search using product name","description":"","id":"f04-product-search-|-user-search-for-product;logged-user-could-search-using-product-name;;4","after":[{"result":{"duration":3372144100,"status":"passed"},"match":{"location":"org.example.Step_Definitions.Hooks.close_browser()"}}],"type":"scenario","keyword":"Scenario Outline","steps":[{"result":{"duration":90990800,"status":"passed"},"line":7,"name":"user click on search box and write \"nike\"","match":{"arguments":[{"val":"\"nike\"","offset":35}],"location":"org.example.Step_Definitions.D04_ProductSearch_StepDefinitions.searchBox(java.lang.String)"},"keyword":"When "},{"result":{"duration":659231100,"status":"passed"},"line":8,"name":"user press on the search button","match":{"location":"org.example.Step_Definitions.D04_ProductSearch_StepDefinitions.searchButton()"},"keyword":"And "},{"result":{"duration":127503300,"status":"passed"},"line":9,"name":"\"nike\" should appear successfully","match":{"arguments":[{"val":"\"nike\"","offset":0}],"location":"org.example.Step_Definitions.D04_ProductSearch_StepDefinitions.productFoundSuccess(java.lang.String)"},"keyword":"Then "}],"tags":[{"name":"@smoke"}]},{"line":4,"name":"user enters \"aessam@gmail.com\" and \"123456\"","description":"","type":"background","keyword":"Background","steps":[]},{"start_timestamp":"2022-12-14T22:02:52.772Z","before":[{"result":{"duration":1601427600,"status":"passed"},"match":{"location":"org.example.Step_Definitions.Hooks.open_browser()"}}],"line":24,"name":"Logged user could search for product using sku","description":"","id":"f04-product-search-|-user-search-for-product;logged-user-could-search-for-product-using-sku;;2","after":[{"result":{"duration":4159134500,"status":"passed"},"match":{"location":"org.example.Step_Definitions.Hooks.close_browser()"}}],"type":"scenario","keyword":"Scenario Outline","steps":[{"result":{"duration":100011900,"status":"passed"},"line":18,"name":"user click on search box and write \"SCI_FAITH\"","match":{"arguments":[{"val":"\"SCI_FAITH\"","offset":35}],"location":"org.example.Step_Definitions.D04_ProductSearch_StepDefinitions.searchBox(java.lang.String)"},"keyword":"When "},{"result":{"duration":668896000,"status":"passed"},"line":19,"name":"user press on the search button","match":{"location":"org.example.Step_Definitions.D04_ProductSearch_StepDefinitions.searchButton()"},"keyword":"And "},{"result":{"duration":1227439000,"status":"passed"},"line":20,"name":"user click on the product in search result","match":{"location":"org.example.Step_Definitions.D04_ProductSearch_StepDefinitions.clickOnProduct()"},"keyword":"And "},{"result":{"duration":29018500,"status":"passed"},"line":21,"name":"\"SCI_FAITH\" should appear successfully in product page","match":{"arguments":[{"val":"\"SCI_FAITH\"","offset":0}],"location":"org.example.Step_Definitions.D04_ProductSearch_StepDefinitions.serialNFound(java.lang.String)"},"keyword":"Then "}],"tags":[{"name":"@smoke"}]},{"line":4,"name":"user enters \"aessam@gmail.com\" and \"123456\"","description":"","type":"background","keyword":"Background","steps":[]},{"start_timestamp":"2022-12-14T22:03:00.570Z","before":[{"result":{"duration":2169297700,"status":"passed"},"match":{"location":"org.example.Step_Definitions.Hooks.open_browser()"}}],"line":25,"name":"Logged user could search for product using sku","description":"","id":"f04-product-search-|-user-search-for-product;logged-user-could-search-for-product-using-sku;;3","after":[{"result":{"duration":4224838500,"status":"passed"},"match":{"location":"org.example.Step_Definitions.Hooks.close_browser()"}}],"type":"scenario","keyword":"Scenario Outline","steps":[{"result":{"duration":95008300,"status":"passed"},"line":18,"name":"user click on search box and write \"APPLE_CAM\"","match":{"arguments":[{"val":"\"APPLE_CAM\"","offset":35}],"location":"org.example.Step_Definitions.D04_ProductSearch_StepDefinitions.searchBox(java.lang.String)"},"keyword":"When "},{"result":{"duration":666605500,"status":"passed"},"line":19,"name":"user press on the search button","match":{"location":"org.example.Step_Definitions.D04_ProductSearch_StepDefinitions.searchButton()"},"keyword":"And "},{"result":{"duration":1214683400,"status":"passed"},"line":20,"name":"user click on the product in search result","match":{"location":"org.example.Step_Definitions.D04_ProductSearch_StepDefinitions.clickOnProduct()"},"keyword":"And "},{"result":{"duration":27215000,"status":"passed"},"line":21,"name":"\"APPLE_CAM\" should appear successfully in product page","match":{"arguments":[{"val":"\"APPLE_CAM\"","offset":0}],"location":"org.example.Step_Definitions.D04_ProductSearch_StepDefinitions.serialNFound(java.lang.String)"},"keyword":"Then "}],"tags":[{"name":"@smoke"}]},{"line":4,"name":"user enters \"aessam@gmail.com\" and \"123456\"","description":"","type":"background","keyword":"Background","steps":[]},{"start_timestamp":"2022-12-14T22:03:08.980Z","before":[{"result":{"duration":1580819300,"status":"passed"},"match":{"location":"org.example.Step_Definitions.Hooks.open_browser()"}}],"line":26,"name":"Logged user could search for product using sku","description":"","id":"f04-product-search-|-user-search-for-product;logged-user-could-search-for-product-using-sku;;4","after":[{"result":{"duration":3393825400,"status":"passed"},"match":{"location":"org.example.Step_Definitions.Hooks.close_browser()"}}],"type":"scenario","keyword":"Scenario Outline","steps":[{"result":{"duration":113005400,"status":"passed"},"line":18,"name":"user click on search box and write \"SF_PRO_11\"","match":{"arguments":[{"val":"\"SF_PRO_11\"","offset":35}],"location":"org.example.Step_Definitions.D04_ProductSearch_StepDefinitions.searchBox(java.lang.String)"},"keyword":"When "},{"result":{"duration":642467400,"status":"passed"},"line":19,"name":"user press on the search button","match":{"location":"org.example.Step_Definitions.D04_ProductSearch_StepDefinitions.searchButton()"},"keyword":"And "},{"result":{"duration":1794280400,"status":"passed"},"line":20,"name":"user click on the product in search result","match":{"location":"org.example.Step_Definitions.D04_ProductSearch_StepDefinitions.clickOnProduct()"},"keyword":"And "},{"result":{"duration":28019800,"status":"passed"},"line":21,"name":"\"SF_PRO_11\" should appear successfully in product page","match":{"arguments":[{"val":"\"SF_PRO_11\"","offset":0}],"location":"org.example.Step_Definitions.D04_ProductSearch_StepDefinitions.serialNFound(java.lang.String)"},"keyword":"Then "}],"tags":[{"name":"@smoke"}]}],"name":"F04_Product Search | user search for product","description":"","id":"f04-product-search-|-user-search-for-product","keyword":"Feature","uri":"file:src/main/resources/Features_Folder/F04_Product_Search.feature","tags":[{"name":"@smoke","type":"Tag","location":{"line":1,"column":1}}]},{"line":2,"elements":[{"start_timestamp":"2022-12-14T22:03:16.542Z","before":[{"result":{"duration":1628773300,"status":"passed"},"match":{"location":"org.example.Step_Definitions.Hooks.open_browser()"}}],"line":6,"name":"Logged User could choose US currency","description":"","id":"f05-switching-currencies-|-user-switch-between-us-and-euro-currencies;logged-user-could-choose-us-currency","after":[{"result":{"duration":4181777500,"status":"passed"},"match":{"location":"org.example.Step_Definitions.Hooks.close_browser()"}}],"type":"scenario","keyword":"Scenario","steps":[{"result":{"duration":75002500,"status":"passed"},"line":7,"name":"user click on the currency selector and choose the US currency","match":{"location":"org.example.Step_Definitions.D05_SwitchCurrencies_StepDifinitions.usDollar_Selection()"},"keyword":"When "},{"result":{"duration":160009800,"status":"passed"},"line":8,"name":"US dollar symbol is chosen and displayed on all products","match":{"location":"org.example.Step_Definitions.D05_SwitchCurrencies_StepDifinitions.usDollar_Chosen_Successfully()"},"keyword":"Then "}],"tags":[{"name":"@smoke"}]},{"start_timestamp":"2022-12-14T22:03:22.597Z","before":[{"result":{"duration":2124079300,"status":"passed"},"match":{"location":"org.example.Step_Definitions.Hooks.open_browser()"}}],"line":11,"name":"Logged User could choose Euro currency","description":"","id":"f05-switching-currencies-|-user-switch-between-us-and-euro-currencies;logged-user-could-choose-euro-currency","after":[{"result":{"duration":3302383300,"status":"passed"},"match":{"location":"org.example.Step_Definitions.Hooks.close_browser()"}}],"type":"scenario","keyword":"Scenario","steps":[{"result":{"duration":1185040000,"status":"passed"},"line":12,"name":"user click on the currency selector and choose the Euro currency","match":{"location":"org.example.Step_Definitions.D05_SwitchCurrencies_StepDifinitions.euro_Selection()"},"keyword":"When "},{"result":{"duration":150449600,"status":"passed"},"line":13,"name":"Euro symbol is chosen and displayed on all products","match":{"location":"org.example.Step_Definitions.D05_SwitchCurrencies_StepDifinitions.Euro_Chosen_Successfully()"},"keyword":"Then "}],"tags":[{"name":"@smoke"}]}],"name":"F05_Switching Currencies | user switch between US and Euro currencies","description":"","id":"f05-switching-currencies-|-user-switch-between-us-and-euro-currencies","keyword":"Feature","uri":"file:src/main/resources/Features_Folder/F05_Switch_Currencies.feature","tags":[{"name":"@smoke","type":"Tag","location":{"line":1,"column":1}}]},{"line":2,"elements":[{"start_timestamp":"2022-12-14T22:03:29.370Z","before":[{"result":{"duration":1692239700,"status":"passed"},"match":{"location":"org.example.Step_Definitions.Hooks.open_browser()"}}],"line":5,"name":"Logged user could hover on different sub categories","description":"","id":"f06-hover-on-categories-|-user-hover-on-categories;logged-user-could-hover-on-different-sub-categories","after":[{"result":{"duration":4187890500,"status":"passed"},"match":{"location":"org.example.Step_Definitions.Hooks.close_browser()"}}],"type":"scenario","keyword":"Scenario","steps":[{"result":{"duration":236137900,"status":"passed"},"line":6,"name":"user select random one of the three main categories","match":{"location":"org.example.Step_Definitions.D06_HoverOnCategories_StepDefinitions.categorySelection()"},"keyword":"When "},{"result":{"duration":840210000,"status":"passed"},"line":7,"name":"user could hover on sub categories of the selected main category","match":{"location":"org.example.Step_Definitions.D06_HoverOnCategories_StepDefinitions.hoverSubCategory()"},"keyword":"Then "}],"tags":[{"name":"@smoke"}]}],"name":"F06_Hover On Categories | user hover on categories","description":"","id":"f06-hover-on-categories-|-user-hover-on-categories","keyword":"Feature","uri":"file:src/main/resources/Features_Folder/F06_HoverOnCategories.feature","tags":[{"name":"@smoke","type":"Tag","location":{"line":1,"column":1}}]},{"line":2,"elements":[{"start_timestamp":"2022-12-14T22:03:36.333Z","before":[{"result":{"duration":1701396300,"status":"passed"},"match":{"location":"org.example.Step_Definitions.Hooks.open_browser()"}}],"line":5,"name":"first slider is clickable on home page","description":"","id":"f07-home-sliders-|-user-clicks-on-home-sliders;first-slider-is-clickable-on-home-page","after":[{"result":{"duration":3302383000,"status":"passed"},"match":{"location":"org.example.Step_Definitions.Hooks.close_browser()"}}],"type":"scenario","keyword":"Scenario","steps":[{"result":{"duration":406339000,"status":"passed"},"line":6,"name":"user clicks on the Nokia Lumia 1020 slider","match":{"location":"org.example.Step_Definitions.D07_HomeSliders_StepDefinitions.click_NokiaSlider()"},"keyword":"When "},{"result":{"error_message":"java.lang.AssertionError: expected [https://demo.nopcommerce.com/iphone-6] but found [https://demo.nopcommerce.com/]\r\n\tat org.testng.Assert.fail(Assert.java:110)\r\n\tat org.testng.Assert.failNotEquals(Assert.java:1413)\r\n\tat org.testng.Assert.assertEqualsImpl(Assert.java:149)\r\n\tat org.testng.Assert.assertEquals(Assert.java:131)\r\n\tat org.testng.Assert.assertEquals(Assert.java:655)\r\n\tat org.testng.Assert.assertEquals(Assert.java:665)\r\n\tat org.example.Step_Definitions.D07_HomeSliders_StepDefinitions.iphone_Page(D07_HomeSliders_StepDefinitions.java:40)\r\n\tat ✽.user should be directed to Nokia Lumia 1020 page(file:///D:/E-Commerce%20Website%20Project/E-Commerce_Website_Testing/src/main/resources/Features_Folder/F07_Home_Sliders.feature:7)\r\n","duration":18999600,"status":"failed"},"line":7,"name":"user should be directed to Nokia Lumia 1020 page","match":{"location":"org.example.Step_Definitions.D07_HomeSliders_StepDefinitions.iphone_Page()"},"keyword":"Then "}],"tags":[{"name":"@smoke"}]},{"start_timestamp":"2022-12-14T22:03:41.769Z","before":[{"result":{"duration":1646996000,"status":"passed"},"match":{"location":"org.example.Step_Definitions.Hooks.open_browser()"}}],"line":11,"name":"second slider is clickable on home page","description":"","id":"f07-home-sliders-|-user-clicks-on-home-sliders;second-slider-is-clickable-on-home-page","after":[{"result":{"duration":4269832000,"status":"passed"},"match":{"location":"org.example.Step_Definitions.Hooks.close_browser()"}}],"type":"scenario","keyword":"Scenario","steps":[{"result":{"duration":416286100,"status":"passed"},"line":12,"name":"user clicks on the iPhone slider","match":{"location":"org.example.Step_Definitions.D07_HomeSliders_StepDefinitions.click_IPhoneSlider()"},"keyword":"When "},{"result":{"error_message":"java.lang.AssertionError: expected [https://demo.nopcommerce.com/nokia-lumia-1020] but found [https://demo.nopcommerce.com/]\r\n\tat org.testng.Assert.fail(Assert.java:110)\r\n\tat org.testng.Assert.failNotEquals(Assert.java:1413)\r\n\tat org.testng.Assert.assertEqualsImpl(Assert.java:149)\r\n\tat org.testng.Assert.assertEquals(Assert.java:131)\r\n\tat org.testng.Assert.assertEquals(Assert.java:655)\r\n\tat org.testng.Assert.assertEquals(Assert.java:665)\r\n\tat org.example.Step_Definitions.D07_HomeSliders_StepDefinitions.nokia_Page(D07_HomeSliders_StepDefinitions.java:25)\r\n\tat ✽.user should be directed to iPhone page(file:///D:/E-Commerce%20Website%20Project/E-Commerce_Website_Testing/src/main/resources/Features_Folder/F07_Home_Sliders.feature:13)\r\n","duration":9996800,"status":"failed"},"line":13,"name":"user should be directed to iPhone page","match":{"location":"org.example.Step_Definitions.D07_HomeSliders_StepDefinitions.nokia_Page()"},"keyword":"Then "}],"tags":[{"name":"@smoke"}]}],"name":"F07_Home Sliders | user clicks on home sliders","description":"","id":"f07-home-sliders-|-user-clicks-on-home-sliders","keyword":"Feature","uri":"file:src/main/resources/Features_Folder/F07_Home_Sliders.feature","tags":[{"name":"@smoke","type":"Tag","location":{"line":1,"column":1}}]},{"line":2,"elements":[{"start_timestamp":"2022-12-14T22:03:48.120Z","before":[{"result":{"duration":1680622900,"status":"passed"},"match":{"location":"org.example.Step_Definitions.Hooks.open_browser()"}}],"line":5,"name":"user opens facebook link","description":"","id":"f08-follow-us--|-user-clicks-on-follow-us-icons;user-opens-facebook-link","after":[{"result":{"duration":3309668700,"status":"passed"},"match":{"location":"org.example.Step_Definitions.Hooks.close_browser()"}}],"type":"scenario","keyword":"Scenario","steps":[{"result":{"duration":122011100,"status":"passed"},"line":6,"name":"user clicks on facebook link","match":{"location":"org.example.Step_Definitions.D08_FollowUs_StepDefinitions.click_facebook()"},"keyword":"When "},{"result":{"duration":3019498600,"status":"passed"},"line":7,"name":"user should be directed to the website facabook page","match":{"location":"org.example.Step_Definitions.D08_FollowUs_StepDefinitions.facebookPage()"},"keyword":"Then "}],"tags":[{"name":"@smoke"}]},{"start_timestamp":"2022-12-14T22:03:56.258Z","before":[{"result":{"duration":1708030500,"status":"passed"},"match":{"location":"org.example.Step_Definitions.Hooks.open_browser()"}}],"line":10,"name":"user opens twitter link","description":"","id":"f08-follow-us--|-user-clicks-on-follow-us-icons;user-opens-twitter-link","after":[{"result":{"duration":3321494600,"status":"passed"},"match":{"location":"org.example.Step_Definitions.Hooks.close_browser()"}}],"type":"scenario","keyword":"Scenario","steps":[{"result":{"duration":124009300,"status":"passed"},"line":11,"name":"user clicks on twitter link","match":{"location":"org.example.Step_Definitions.D08_FollowUs_StepDefinitions.click_twitter()"},"keyword":"When "},{"result":{"duration":3138125300,"status":"passed"},"line":12,"name":"user should be directed to the website twitter page","match":{"location":"org.example.Step_Definitions.D08_FollowUs_StepDefinitions.twitter()"},"keyword":"Then "}],"tags":[{"name":"@smoke"}]},{"start_timestamp":"2022-12-14T22:04:04.559Z","before":[{"result":{"duration":1766968000,"status":"passed"},"match":{"location":"org.example.Step_Definitions.Hooks.open_browser()"}}],"line":15,"name":"user opens rss link","description":"","id":"f08-follow-us--|-user-clicks-on-follow-us-icons;user-opens-rss-link","after":[{"result":{"duration":3228269700,"status":"passed"},"match":{"location":"org.example.Step_Definitions.Hooks.close_browser()"}}],"type":"scenario","keyword":"Scenario","steps":[{"result":{"duration":385398700,"status":"passed"},"line":16,"name":"user clicks on rss link","match":{"location":"org.example.Step_Definitions.D08_FollowUs_StepDefinitions.click_rss()"},"keyword":"When "},{"result":{"error_message":"java.lang.IndexOutOfBoundsException: Index 1 out of bounds for length 1\r\n\tat java.base/jdk.internal.util.Preconditions.outOfBounds(Preconditions.java:100)\r\n\tat java.base/jdk.internal.util.Preconditions.outOfBoundsCheckIndex(Preconditions.java:106)\r\n\tat java.base/jdk.internal.util.Preconditions.checkIndex(Preconditions.java:302)\r\n\tat java.base/java.util.Objects.checkIndex(Objects.java:385)\r\n\tat java.base/java.util.ArrayList.get(ArrayList.java:427)\r\n\tat org.example.Step_Definitions.D08_FollowUs_StepDefinitions.rss(D08_FollowUs_StepDefinitions.java:73)\r\n\tat ✽.user should be directed to the website rss page(file:///D:/E-Commerce%20Website%20Project/E-Commerce_Website_Testing/src/main/resources/Features_Folder/F08_FollowUs.feature:17)\r\n","duration":3012382500,"status":"failed"},"line":17,"name":"user should be directed to the website rss page","match":{"location":"org.example.Step_Definitions.D08_FollowUs_StepDefinitions.rss()"},"keyword":"Then "}],"tags":[{"name":"@smoke"}]},{"start_timestamp":"2022-12-14T22:04:12.961Z","before":[{"result":{"duration":1928283600,"status":"passed"},"match":{"location":"org.example.Step_Definitions.Hooks.open_browser()"}}],"line":20,"name":"user opens youtube link","description":"","id":"f08-follow-us--|-user-clicks-on-follow-us-icons;user-opens-youtube-link","after":[{"result":{"duration":3683886000,"status":"passed"},"match":{"location":"org.example.Step_Definitions.Hooks.close_browser()"}}],"type":"scenario","keyword":"Scenario","steps":[{"result":{"duration":110011600,"status":"passed"},"line":21,"name":"user clicks on youtube link","match":{"location":"org.example.Step_Definitions.D08_FollowUs_StepDefinitions.click_youtube()"},"keyword":"When "},{"result":{"duration":5454562300,"status":"passed"},"line":22,"name":"user should be directed to the website youtube page","match":{"location":"org.example.Step_Definitions.D08_FollowUs_StepDefinitions.youtube()"},"keyword":"Then "}],"tags":[{"name":"@smoke"}]}],"name":"F08_Follow Us  | User clicks on follow us icons","description":"","id":"f08-follow-us--|-user-clicks-on-follow-us-icons","keyword":"Feature","uri":"file:src/main/resources/Features_Folder/F08_FollowUs.feature","tags":[{"name":"@smoke","type":"Tag","location":{"line":1,"column":1}}]},{"line":2,"elements":[{"start_timestamp":"2022-12-14T22:04:24.144Z","before":[{"result":{"duration":1898711500,"status":"passed"},"match":{"location":"org.example.Step_Definitions.Hooks.open_browser()"}}],"line":4,"name":"user could add different products to Wishlist","description":"","id":"f09-wishlist-|-user-add-products-to-wishlist;user-could-add-different-products-to-wishlist","after":[{"result":{"duration":4193662500,"status":"passed"},"match":{"location":"org.example.Step_Definitions.Hooks.close_browser()"}}],"type":"scenario","keyword":"Scenario","steps":[{"result":{"duration":62001100,"status":"passed"},"line":5,"name":"user clicks on the wishlist button","match":{"location":"org.example.Step_Definitions.D09_Wishlist_StepDefinitions.click_wishlist()"},"keyword":"When "},{"result":{"duration":363259300,"status":"passed"},"line":6,"name":"the product is added to wishlist and success message appears","match":{"location":"org.example.Step_Definitions.D09_Wishlist_StepDefinitions.wishlist_success()"},"keyword":"Then "}],"tags":[{"name":"@smoke"}]},{"start_timestamp":"2022-12-14T22:04:30.671Z","before":[{"result":{"duration":1663652500,"status":"passed"},"match":{"location":"org.example.Step_Definitions.Hooks.open_browser()"}}],"line":9,"name":"user could click on \"Wishlist\" Tab","description":"","id":"f09-wishlist-|-user-add-products-to-wishlist;user-could-click-on-\"wishlist\"-tab","after":[{"result":{"duration":3294651400,"status":"passed"},"match":{"location":"org.example.Step_Definitions.Hooks.close_browser()"}}],"type":"scenario","keyword":"Scenario","steps":[{"result":{"duration":69004500,"status":"passed"},"line":10,"name":"user clicks on the wishlist button","match":{"location":"org.example.Step_Definitions.D09_Wishlist_StepDefinitions.click_wishlist()"},"keyword":"When "},{"result":{"error_message":"org.openqa.selenium.TimeoutException: Expected condition failed: waiting for element to no longer be visible: By.cssSelector: div[class=\"bar-notification success\"] (tried for 4 second(s) with 500 milliseconds interval)\nBuild info: version: '4.7.1', revision: 'c6795baf1a3'\nSystem info: os.name: 'Windows 10', os.arch: 'amd64', os.version: '10.0', java.version: '19.0.1'\nDriver info: org.openqa.selenium.chrome.ChromeDriver\nCapabilities {acceptInsecureCerts: false, browserName: chrome, browserVersion: 108.0.5359.100, chrome: {chromedriverVersion: 108.0.5359.71 (1e0e3868ee06..., userDataDir: C:\\Users\\745G5~1\\AppData\\Lo...}, goog:chromeOptions: {debuggerAddress: localhost:52079}, networkConnectionEnabled: false, pageLoadStrategy: normal, platformName: WINDOWS, proxy: Proxy(), se:cdp: ws://localhost:52079/devtoo..., se:cdpVersion: 108.0.5359.100, setWindowRect: true, strictFileInteractability: false, timeouts: {implicit: 0, pageLoad: 300000, script: 30000}, unhandledPromptBehavior: dismiss and notify, webauthn:extension:credBlob: true, webauthn:extension:largeBlob: true, webauthn:virtualAuthenticators: true}\nSession ID: c69e01cdd4c56a6d97dd051c4b6fa070\r\n\tat org.openqa.selenium.support.ui.WebDriverWait.timeoutException(WebDriverWait.java:87)\r\n\tat org.openqa.selenium.support.ui.FluentWait.until(FluentWait.java:231)\r\n\tat org.example.Step_Definitions.D09_Wishlist_StepDefinitions.click_wishlistTab(D09_Wishlist_StepDefinitions.java:50)\r\n\tat ✽.user waits until success message disappears and clicks on wishlist Tab(file:///D:/E-Commerce%20Website%20Project/E-Commerce_Website_Testing/src/main/resources/Features_Folder/F09_Wishlist.feature:11)\r\n","duration":4024172400,"status":"failed"},"line":11,"name":"user waits until success message disappears and clicks on wishlist Tab","match":{"location":"org.example.Step_Definitions.D09_Wishlist_StepDefinitions.click_wishlistTab()"},"keyword":"And "},{"result":{"status":"skipped"},"line":12,"name":"product is existed in the wishlist","match":{"location":"org.example.Step_Definitions.D09_Wishlist_StepDefinitions.product_exists()"},"keyword":"Then "}],"tags":[{"name":"@smoke"}]}],"name":"F09_Wishlist | user add products to wishlist","description":"","id":"f09-wishlist-|-user-add-products-to-wishlist","keyword":"Feature","uri":"file:src/main/resources/Features_Folder/F09_Wishlist.feature","tags":[{"name":"@smoke","type":"Tag","location":{"line":1,"column":1}}]}]